gunicorn-stubs/METADATA.toml
gunicorn-stubs/__init__.pyi
gunicorn-stubs/_types.pyi
gunicorn-stubs/arbiter.pyi
gunicorn-stubs/config.pyi
gunicorn-stubs/debug.pyi
gunicorn-stubs/errors.pyi
gunicorn-stubs/glogging.pyi
gunicorn-stubs/pidfile.pyi
gunicorn-stubs/py.typed
gunicorn-stubs/reloader.pyi
gunicorn-stubs/sock.pyi
gunicorn-stubs/systemd.pyi
gunicorn-stubs/util.pyi
gunicorn-stubs/app/__init__.pyi
gunicorn-stubs/app/base.pyi
gunicorn-stubs/app/pasterapp.pyi
gunicorn-stubs/app/wsgiapp.pyi
gunicorn-stubs/http/__init__.pyi
gunicorn-stubs/http/body.pyi
gunicorn-stubs/http/errors.pyi
gunicorn-stubs/http/message.pyi
gunicorn-stubs/http/parser.pyi
gunicorn-stubs/http/unreader.pyi
gunicorn-stubs/http/wsgi.pyi
gunicorn-stubs/instrument/__init__.pyi
gunicorn-stubs/instrument/statsd.pyi
gunicorn-stubs/workers/__init__.pyi
gunicorn-stubs/workers/base.pyi
gunicorn-stubs/workers/base_async.pyi
gunicorn-stubs/workers/geventlet.pyi
gunicorn-stubs/workers/ggevent.pyi
gunicorn-stubs/workers/gthread.pyi
gunicorn-stubs/workers/gtornado.pyi
gunicorn-stubs/workers/sync.pyi
gunicorn-stubs/workers/workertmp.pyi
types_gunicorn-23.0.0.20251001.dist-info/licenses/LICENSE
types_gunicorn-23.0.0.20251001.dist-info/METADATA
types_gunicorn-23.0.0.20251001.dist-info/WHEEL
types_gunicorn-23.0.0.20251001.dist-info/top_level.txt
types_gunicorn-23.0.0.20251001.dist-info/RECORD
